// class version 46.0 (46)
// access flags 0x1
public class com/cedar/cglib/CglibTest$$EnhancerByCGLIB$$257d860e$$FastClassByCGLIB$$ef11584b extends net/sf/cglib/reflect/FastClass {

  // compiled from: <generated>

  // access flags 0x1
  public <init>(Ljava/lang/Class;)V
    ALOAD 0
    ALOAD 1
    INVOKESPECIAL net/sf/cglib/reflect/FastClass.<init> (Ljava/lang/Class;)V
    RETURN
    MAXSTACK = 2
    MAXLOCALS = 2

  // access flags 0x1
  public getIndex(Lnet/sf/cglib/core/Signature;)I
    ALOAD 1
    INVOKEVIRTUAL java/lang/Object.toString ()Ljava/lang/String;
    DUP
    INVOKEVIRTUAL java/lang/Object.hashCode ()I
    LOOKUPSWITCH
      -2055565910: L0
      -1882565338: L1
      -1457535688: L2
      -1411842725: L3
      -894172689: L4
      -623122092: L5
      -508378822: L6
      -419626537: L7
      87735549: L8
      560567118: L9
      811063227: L10
      973717575: L11
      1221173700: L12
      1230699260: L13
      1306468936: L14
      1341835395: L15
      1458503150: L16
      1584330438: L17
      1800494055: L18
      1826985398: L19
      1913648695: L20
      1984935277: L21
      default: L22
   L0
   FRAME FULL [com/cedar/cglib/CglibTest$$EnhancerByCGLIB$$257d860e$$FastClassByCGLIB$$ef11584b net/sf/cglib/core/Signature] [java/lang/String]
    LDC "CGLIB$SET_THREAD_CALLBACKS([Lnet/sf/cglib/proxy/Callback;)V"
    INVOKEVIRTUAL java/lang/Object.equals (Ljava/lang/Object;)Z
    IFEQ L23
    ICONST_4
    IRETURN
   L1
   FRAME FULL [com/cedar/cglib/CglibTest$$EnhancerByCGLIB$$257d860e$$FastClassByCGLIB$$ef11584b net/sf/cglib/core/Signature] [java/lang/String]
    LDC "CGLIB$equals$1(Ljava/lang/Object;)Z"
    INVOKEVIRTUAL java/lang/Object.equals (Ljava/lang/Object;)Z
    IFEQ L23
    BIPUSH 12
    IRETURN
   L2
   FRAME FULL [com/cedar/cglib/CglibTest$$EnhancerByCGLIB$$257d860e$$FastClassByCGLIB$$ef11584b net/sf/cglib/core/Signature] [java/lang/String]
    LDC "CGLIB$STATICHOOK1()V"
    INVOKEVIRTUAL java/lang/Object.equals (Ljava/lang/Object;)Z
    IFEQ L23
    BIPUSH 7
    IRETURN
   L3
   FRAME FULL [com/cedar/cglib/CglibTest$$EnhancerByCGLIB$$257d860e$$FastClassByCGLIB$$ef11584b net/sf/cglib/core/Signature] [java/lang/String]
    LDC "CGLIB$hashCode$3()I"
    INVOKEVIRTUAL java/lang/Object.equals (Ljava/lang/Object;)Z
    IFEQ L23
    BIPUSH 11
    IRETURN
   L4
   FRAME FULL [com/cedar/cglib/CglibTest$$EnhancerByCGLIB$$257d860e$$FastClassByCGLIB$$ef11584b net/sf/cglib/core/Signature] [java/lang/String]
    LDC "newInstance(Lnet/sf/cglib/proxy/Callback;)Ljava/lang/Object;"
    INVOKEVIRTUAL java/lang/Object.equals (Ljava/lang/Object;)Z
    IFEQ L23
    BIPUSH 20
    IRETURN
   L5
   FRAME FULL [com/cedar/cglib/CglibTest$$EnhancerByCGLIB$$257d860e$$FastClassByCGLIB$$ef11584b net/sf/cglib/core/Signature] [java/lang/String]
    LDC "CGLIB$findMethodProxy(Lnet/sf/cglib/core/Signature;)Lnet/sf/cglib/proxy/MethodProxy;"
    INVOKEVIRTUAL java/lang/Object.equals (Ljava/lang/Object;)Z
    IFEQ L23
    BIPUSH 8
    IRETURN
   L6
   FRAME FULL [com/cedar/cglib/CglibTest$$EnhancerByCGLIB$$257d860e$$FastClassByCGLIB$$ef11584b net/sf/cglib/core/Signature] [java/lang/String]
    LDC "clone()Ljava/lang/Object;"
    INVOKEVIRTUAL java/lang/Object.equals (Ljava/lang/Object;)Z
    IFEQ L23
    BIPUSH 17
    IRETURN
   L7
   FRAME FULL [com/cedar/cglib/CglibTest$$EnhancerByCGLIB$$257d860e$$FastClassByCGLIB$$ef11584b net/sf/cglib/core/Signature] [java/lang/String]
    LDC "setCallbacks([Lnet/sf/cglib/proxy/Callback;)V"
    INVOKEVIRTUAL java/lang/Object.equals (Ljava/lang/Object;)Z
    IFEQ L23
    ICONST_2
    IRETURN
   L8
   FRAME FULL [com/cedar/cglib/CglibTest$$EnhancerByCGLIB$$257d860e$$FastClassByCGLIB$$ef11584b net/sf/cglib/core/Signature] [java/lang/String]
    LDC "CGLIB$operate1$0(Ljava/lang/String;)Ljava/lang/String;"
    INVOKEVIRTUAL java/lang/Object.equals (Ljava/lang/Object;)Z
    IFEQ L23
    BIPUSH 10
    IRETURN
   L9
   FRAME FULL [com/cedar/cglib/CglibTest$$EnhancerByCGLIB$$257d860e$$FastClassByCGLIB$$ef11584b net/sf/cglib/core/Signature] [java/lang/String]
    LDC "setCallback(ILnet/sf/cglib/proxy/Callback;)V"
    INVOKEVIRTUAL java/lang/Object.equals (Ljava/lang/Object;)Z
    IFEQ L23
    ICONST_1
    IRETURN
   L10
   FRAME FULL [com/cedar/cglib/CglibTest$$EnhancerByCGLIB$$257d860e$$FastClassByCGLIB$$ef11584b net/sf/cglib/core/Signature] [java/lang/String]
    LDC "newInstance([Ljava/lang/Class;[Ljava/lang/Object;[Lnet/sf/cglib/proxy/Callback;)Ljava/lang/Object;"
    INVOKEVIRTUAL java/lang/Object.equals (Ljava/lang/Object;)Z
    IFEQ L23
    BIPUSH 19
    IRETURN
   L11
   FRAME FULL [com/cedar/cglib/CglibTest$$EnhancerByCGLIB$$257d860e$$FastClassByCGLIB$$ef11584b net/sf/cglib/core/Signature] [java/lang/String]
    LDC "getCallbacks()[Lnet/sf/cglib/proxy/Callback;"
    INVOKEVIRTUAL java/lang/Object.equals (Ljava/lang/Object;)Z
    IFEQ L23
    BIPUSH 6
    IRETURN
   L12
   FRAME FULL [com/cedar/cglib/CglibTest$$EnhancerByCGLIB$$257d860e$$FastClassByCGLIB$$ef11584b net/sf/cglib/core/Signature] [java/lang/String]
    LDC "newInstance([Lnet/sf/cglib/proxy/Callback;)Ljava/lang/Object;"
    INVOKEVIRTUAL java/lang/Object.equals (Ljava/lang/Object;)Z
    IFEQ L23
    BIPUSH 18
    IRETURN
   L13
   FRAME FULL [com/cedar/cglib/CglibTest$$EnhancerByCGLIB$$257d860e$$FastClassByCGLIB$$ef11584b net/sf/cglib/core/Signature] [java/lang/String]
    LDC "getCallback(I)Lnet/sf/cglib/proxy/Callback;"
    INVOKEVIRTUAL java/lang/Object.equals (Ljava/lang/Object;)Z
    IFEQ L23
    ICONST_5
    IRETURN
   L14
   FRAME FULL [com/cedar/cglib/CglibTest$$EnhancerByCGLIB$$257d860e$$FastClassByCGLIB$$ef11584b net/sf/cglib/core/Signature] [java/lang/String]
    LDC "CGLIB$toString$2()Ljava/lang/String;"
    INVOKEVIRTUAL java/lang/Object.equals (Ljava/lang/Object;)Z
    IFEQ L23
    BIPUSH 13
    IRETURN
   L15
   FRAME FULL [com/cedar/cglib/CglibTest$$EnhancerByCGLIB$$257d860e$$FastClassByCGLIB$$ef11584b net/sf/cglib/core/Signature] [java/lang/String]
    LDC "main([Ljava/lang/String;)V"
    INVOKEVIRTUAL java/lang/Object.equals (Ljava/lang/Object;)Z
    IFEQ L23
    BIPUSH 21
    IRETURN
   L16
   FRAME FULL [com/cedar/cglib/CglibTest$$EnhancerByCGLIB$$257d860e$$FastClassByCGLIB$$ef11584b net/sf/cglib/core/Signature] [java/lang/String]
    LDC "operate1(Ljava/lang/String;)Ljava/lang/String;"
    INVOKEVIRTUAL java/lang/Object.equals (Ljava/lang/Object;)Z
    IFEQ L23
    ICONST_0
    IRETURN
   L17
   FRAME FULL [com/cedar/cglib/CglibTest$$EnhancerByCGLIB$$257d860e$$FastClassByCGLIB$$ef11584b net/sf/cglib/core/Signature] [java/lang/String]
    LDC "CGLIB$SET_STATIC_CALLBACKS([Lnet/sf/cglib/proxy/Callback;)V"
    INVOKEVIRTUAL java/lang/Object.equals (Ljava/lang/Object;)Z
    IFEQ L23
    ICONST_3
    IRETURN
   L18
   FRAME FULL [com/cedar/cglib/CglibTest$$EnhancerByCGLIB$$257d860e$$FastClassByCGLIB$$ef11584b net/sf/cglib/core/Signature] [java/lang/String]
    LDC "CGLIB$clone$4()Ljava/lang/Object;"
    INVOKEVIRTUAL java/lang/Object.equals (Ljava/lang/Object;)Z
    IFEQ L23
    BIPUSH 9
    IRETURN
   L19
   FRAME FULL [com/cedar/cglib/CglibTest$$EnhancerByCGLIB$$257d860e$$FastClassByCGLIB$$ef11584b net/sf/cglib/core/Signature] [java/lang/String]
    LDC "equals(Ljava/lang/Object;)Z"
    INVOKEVIRTUAL java/lang/Object.equals (Ljava/lang/Object;)Z
    IFEQ L23
    BIPUSH 14
    IRETURN
   L20
   FRAME FULL [com/cedar/cglib/CglibTest$$EnhancerByCGLIB$$257d860e$$FastClassByCGLIB$$ef11584b net/sf/cglib/core/Signature] [java/lang/String]
    LDC "toString()Ljava/lang/String;"
    INVOKEVIRTUAL java/lang/Object.equals (Ljava/lang/Object;)Z
    IFEQ L23
    BIPUSH 15
    IRETURN
   L21
   FRAME FULL [com/cedar/cglib/CglibTest$$EnhancerByCGLIB$$257d860e$$FastClassByCGLIB$$ef11584b net/sf/cglib/core/Signature] [java/lang/String]
    LDC "hashCode()I"
    INVOKEVIRTUAL java/lang/Object.equals (Ljava/lang/Object;)Z
    IFEQ L23
    BIPUSH 16
    IRETURN
   L22
   FRAME FULL [com/cedar/cglib/CglibTest$$EnhancerByCGLIB$$257d860e$$FastClassByCGLIB$$ef11584b net/sf/cglib/core/Signature] [java/lang/String]
    POP
   L23
   FRAME FULL [com/cedar/cglib/CglibTest$$EnhancerByCGLIB$$257d860e$$FastClassByCGLIB$$ef11584b net/sf/cglib/core/Signature] []
    ICONST_M1
    IRETURN
    MAXSTACK = 2
    MAXLOCALS = 2

  // access flags 0x1
  public getIndex(Ljava/lang/String;[Ljava/lang/Class;)I
    ALOAD 1
    ALOAD 2
    SWAP
    DUP
    INVOKEVIRTUAL java/lang/Object.hashCode ()I
    LOOKUPSWITCH
      -1776922004: L0
      -1295482945: L1
      -1053468136: L2
      -500553939: L3
      -227600004: L4
      -124978609: L5
      -60403779: L6
      -29025555: L7
      3343801: L8
      85179481: L9
      94756189: L10
      147696667: L11
      161998109: L12
      495524492: L13
      1154623345: L14
      1543336189: L15
      1811874389: L16
      1817099975: L17
      1905679803: L18
      1951977610: L19
      default: L20
   L0
   FRAME FULL [com/cedar/cglib/CglibTest$$EnhancerByCGLIB$$257d860e$$FastClassByCGLIB$$ef11584b java/lang/String [Ljava/lang/Class;] [[Ljava/lang/Class; java/lang/String]
    LDC "toString"
    INVOKEVIRTUAL java/lang/Object.equals (Ljava/lang/Object;)Z
    IFEQ L21
    DUP
    ARRAYLENGTH
    TABLESWITCH
      0: L22
      default: L23
   L22
   FRAME FULL [com/cedar/cglib/CglibTest$$EnhancerByCGLIB$$257d860e$$FastClassByCGLIB$$ef11584b java/lang/String [Ljava/lang/Class;] [[Ljava/lang/Class;]
    POP
    BIPUSH 15
    IRETURN
   L23
   FRAME FULL [com/cedar/cglib/CglibTest$$EnhancerByCGLIB$$257d860e$$FastClassByCGLIB$$ef11584b java/lang/String [Ljava/lang/Class;] [[Ljava/lang/Class;]
    GOTO L24
   L1
   FRAME FULL [com/cedar/cglib/CglibTest$$EnhancerByCGLIB$$257d860e$$FastClassByCGLIB$$ef11584b java/lang/String [Ljava/lang/Class;] [[Ljava/lang/Class; java/lang/String]
    LDC "equals"
    INVOKEVIRTUAL java/lang/Object.equals (Ljava/lang/Object;)Z
    IFEQ L21
    DUP
    ARRAYLENGTH
    TABLESWITCH
      1: L25
      default: L26
   L25
   FRAME FULL [com/cedar/cglib/CglibTest$$EnhancerByCGLIB$$257d860e$$FastClassByCGLIB$$ef11584b java/lang/String [Ljava/lang/Class;] [[Ljava/lang/Class;]
    DUP
    ICONST_0
    AALOAD
    INVOKEVIRTUAL java/lang/Class.getName ()Ljava/lang/String;
    LDC "java.lang.Object"
    INVOKEVIRTUAL java/lang/Object.equals (Ljava/lang/Object;)Z
    IFEQ L24
    POP
    BIPUSH 14
    IRETURN
   L26
   FRAME FULL [com/cedar/cglib/CglibTest$$EnhancerByCGLIB$$257d860e$$FastClassByCGLIB$$ef11584b java/lang/String [Ljava/lang/Class;] [[Ljava/lang/Class;]
    GOTO L24
   L2
   FRAME FULL [com/cedar/cglib/CglibTest$$EnhancerByCGLIB$$257d860e$$FastClassByCGLIB$$ef11584b java/lang/String [Ljava/lang/Class;] [[Ljava/lang/Class; java/lang/String]
    LDC "getCallbacks"
    INVOKEVIRTUAL java/lang/Object.equals (Ljava/lang/Object;)Z
    IFEQ L21
    DUP
    ARRAYLENGTH
    TABLESWITCH
      0: L27
      default: L28
   L27
   FRAME FULL [com/cedar/cglib/CglibTest$$EnhancerByCGLIB$$257d860e$$FastClassByCGLIB$$ef11584b java/lang/String [Ljava/lang/Class;] [[Ljava/lang/Class;]
    POP
    BIPUSH 6
    IRETURN
   L28
   FRAME FULL [com/cedar/cglib/CglibTest$$EnhancerByCGLIB$$257d860e$$FastClassByCGLIB$$ef11584b java/lang/String [Ljava/lang/Class;] [[Ljava/lang/Class;]
    GOTO L24
   L3
   FRAME FULL [com/cedar/cglib/CglibTest$$EnhancerByCGLIB$$257d860e$$FastClassByCGLIB$$ef11584b java/lang/String [Ljava/lang/Class;] [[Ljava/lang/Class; java/lang/String]
    LDC "operate1"
    INVOKEVIRTUAL java/lang/Object.equals (Ljava/lang/Object;)Z
    IFEQ L21
    DUP
    ARRAYLENGTH
    TABLESWITCH
      1: L29
      default: L30
   L29
   FRAME FULL [com/cedar/cglib/CglibTest$$EnhancerByCGLIB$$257d860e$$FastClassByCGLIB$$ef11584b java/lang/String [Ljava/lang/Class;] [[Ljava/lang/Class;]
    DUP
    ICONST_0
    AALOAD
    INVOKEVIRTUAL java/lang/Class.getName ()Ljava/lang/String;
    LDC "java.lang.String"
    INVOKEVIRTUAL java/lang/Object.equals (Ljava/lang/Object;)Z
    IFEQ L24
    POP
    ICONST_0
    IRETURN
   L30
   FRAME FULL [com/cedar/cglib/CglibTest$$EnhancerByCGLIB$$257d860e$$FastClassByCGLIB$$ef11584b java/lang/String [Ljava/lang/Class;] [[Ljava/lang/Class;]
    GOTO L24
   L4
   FRAME FULL [com/cedar/cglib/CglibTest$$EnhancerByCGLIB$$257d860e$$FastClassByCGLIB$$ef11584b java/lang/String [Ljava/lang/Class;] [[Ljava/lang/Class; java/lang/String]
    LDC "CGLIB$operate1$0"
    INVOKEVIRTUAL java/lang/Object.equals (Ljava/lang/Object;)Z
    IFEQ L21
    DUP
    ARRAYLENGTH
    TABLESWITCH
      1: L31
      default: L32
   L31
   FRAME FULL [com/cedar/cglib/CglibTest$$EnhancerByCGLIB$$257d860e$$FastClassByCGLIB$$ef11584b java/lang/String [Ljava/lang/Class;] [[Ljava/lang/Class;]
    DUP
    ICONST_0
    AALOAD
    INVOKEVIRTUAL java/lang/Class.getName ()Ljava/lang/String;
    LDC "java.lang.String"
    INVOKEVIRTUAL java/lang/Object.equals (Ljava/lang/Object;)Z
    IFEQ L24
    POP
    BIPUSH 10
    IRETURN
   L32
   FRAME FULL [com/cedar/cglib/CglibTest$$EnhancerByCGLIB$$257d860e$$FastClassByCGLIB$$ef11584b java/lang/String [Ljava/lang/Class;] [[Ljava/lang/Class;]
    GOTO L24
   L5
   FRAME FULL [com/cedar/cglib/CglibTest$$EnhancerByCGLIB$$257d860e$$FastClassByCGLIB$$ef11584b java/lang/String [Ljava/lang/Class;] [[Ljava/lang/Class; java/lang/String]
    LDC "CGLIB$equals$1"
    INVOKEVIRTUAL java/lang/Object.equals (Ljava/lang/Object;)Z
    IFEQ L21
    DUP
    ARRAYLENGTH
    TABLESWITCH
      1: L33
      default: L34
   L33
   FRAME FULL [com/cedar/cglib/CglibTest$$EnhancerByCGLIB$$257d860e$$FastClassByCGLIB$$ef11584b java/lang/String [Ljava/lang/Class;] [[Ljava/lang/Class;]
    DUP
    ICONST_0
    AALOAD
    INVOKEVIRTUAL java/lang/Class.getName ()Ljava/lang/String;
    LDC "java.lang.Object"
    INVOKEVIRTUAL java/lang/Object.equals (Ljava/lang/Object;)Z
    IFEQ L24
    POP
    BIPUSH 12
    IRETURN
   L34
   FRAME FULL [com/cedar/cglib/CglibTest$$EnhancerByCGLIB$$257d860e$$FastClassByCGLIB$$ef11584b java/lang/String [Ljava/lang/Class;] [[Ljava/lang/Class;]
    GOTO L24
   L6
   FRAME FULL [com/cedar/cglib/CglibTest$$EnhancerByCGLIB$$257d860e$$FastClassByCGLIB$$ef11584b java/lang/String [Ljava/lang/Class;] [[Ljava/lang/Class; java/lang/String]
    LDC "CGLIB$SET_STATIC_CALLBACKS"
    INVOKEVIRTUAL java/lang/Object.equals (Ljava/lang/Object;)Z
    IFEQ L21
    DUP
    ARRAYLENGTH
    TABLESWITCH
      1: L35
      default: L36
   L35
   FRAME FULL [com/cedar/cglib/CglibTest$$EnhancerByCGLIB$$257d860e$$FastClassByCGLIB$$ef11584b java/lang/String [Ljava/lang/Class;] [[Ljava/lang/Class;]
    DUP
    ICONST_0
    AALOAD
    INVOKEVIRTUAL java/lang/Class.getName ()Ljava/lang/String;
    LDC "[Lnet.sf.cglib.proxy.Callback;"
    INVOKEVIRTUAL java/lang/Object.equals (Ljava/lang/Object;)Z
    IFEQ L24
    POP
    ICONST_3
    IRETURN
   L36
   FRAME FULL [com/cedar/cglib/CglibTest$$EnhancerByCGLIB$$257d860e$$FastClassByCGLIB$$ef11584b java/lang/String [Ljava/lang/Class;] [[Ljava/lang/Class;]
    GOTO L24
   L7
   FRAME FULL [com/cedar/cglib/CglibTest$$EnhancerByCGLIB$$257d860e$$FastClassByCGLIB$$ef11584b java/lang/String [Ljava/lang/Class;] [[Ljava/lang/Class; java/lang/String]
    LDC "CGLIB$hashCode$3"
    INVOKEVIRTUAL java/lang/Object.equals (Ljava/lang/Object;)Z
    IFEQ L21
    DUP
    ARRAYLENGTH
    TABLESWITCH
      0: L37
      default: L38
   L37
   FRAME FULL [com/cedar/cglib/CglibTest$$EnhancerByCGLIB$$257d860e$$FastClassByCGLIB$$ef11584b java/lang/String [Ljava/lang/Class;] [[Ljava/lang/Class;]
    POP
    BIPUSH 11
    IRETURN
   L38
   FRAME FULL [com/cedar/cglib/CglibTest$$EnhancerByCGLIB$$257d860e$$FastClassByCGLIB$$ef11584b java/lang/String [Ljava/lang/Class;] [[Ljava/lang/Class;]
    GOTO L24
   L8
   FRAME FULL [com/cedar/cglib/CglibTest$$EnhancerByCGLIB$$257d860e$$FastClassByCGLIB$$ef11584b java/lang/String [Ljava/lang/Class;] [[Ljava/lang/Class; java/lang/String]
    LDC "main"
    INVOKEVIRTUAL java/lang/Object.equals (Ljava/lang/Object;)Z
    IFEQ L21
    DUP
    ARRAYLENGTH
    TABLESWITCH
      1: L39
      default: L40
   L39
   FRAME FULL [com/cedar/cglib/CglibTest$$EnhancerByCGLIB$$257d860e$$FastClassByCGLIB$$ef11584b java/lang/String [Ljava/lang/Class;] [[Ljava/lang/Class;]
    DUP
    ICONST_0
    AALOAD
    INVOKEVIRTUAL java/lang/Class.getName ()Ljava/lang/String;
    LDC "[Ljava.lang.String;"
    INVOKEVIRTUAL java/lang/Object.equals (Ljava/lang/Object;)Z
    IFEQ L24
    POP
    BIPUSH 21
    IRETURN
   L40
   FRAME FULL [com/cedar/cglib/CglibTest$$EnhancerByCGLIB$$257d860e$$FastClassByCGLIB$$ef11584b java/lang/String [Ljava/lang/Class;] [[Ljava/lang/Class;]
    GOTO L24
   L9
   FRAME FULL [com/cedar/cglib/CglibTest$$EnhancerByCGLIB$$257d860e$$FastClassByCGLIB$$ef11584b java/lang/String [Ljava/lang/Class;] [[Ljava/lang/Class; java/lang/String]
    LDC "CGLIB$SET_THREAD_CALLBACKS"
    INVOKEVIRTUAL java/lang/Object.equals (Ljava/lang/Object;)Z
    IFEQ L21
    DUP
    ARRAYLENGTH
    TABLESWITCH
      1: L41
      default: L42
   L41
   FRAME FULL [com/cedar/cglib/CglibTest$$EnhancerByCGLIB$$257d860e$$FastClassByCGLIB$$ef11584b java/lang/String [Ljava/lang/Class;] [[Ljava/lang/Class;]
    DUP
    ICONST_0
    AALOAD
    INVOKEVIRTUAL java/lang/Class.getName ()Ljava/lang/String;
    LDC "[Lnet.sf.cglib.proxy.Callback;"
    INVOKEVIRTUAL java/lang/Object.equals (Ljava/lang/Object;)Z
    IFEQ L24
    POP
    ICONST_4
    IRETURN
   L42
   FRAME FULL [com/cedar/cglib/CglibTest$$EnhancerByCGLIB$$257d860e$$FastClassByCGLIB$$ef11584b java/lang/String [Ljava/lang/Class;] [[Ljava/lang/Class;]
    GOTO L24
   L10
   FRAME FULL [com/cedar/cglib/CglibTest$$EnhancerByCGLIB$$257d860e$$FastClassByCGLIB$$ef11584b java/lang/String [Ljava/lang/Class;] [[Ljava/lang/Class; java/lang/String]
    LDC "clone"
    INVOKEVIRTUAL java/lang/Object.equals (Ljava/lang/Object;)Z
    IFEQ L21
    DUP
    ARRAYLENGTH
    TABLESWITCH
      0: L43
      default: L44
   L43
   FRAME FULL [com/cedar/cglib/CglibTest$$EnhancerByCGLIB$$257d860e$$FastClassByCGLIB$$ef11584b java/lang/String [Ljava/lang/Class;] [[Ljava/lang/Class;]
    POP
    BIPUSH 17
    IRETURN
   L44
   FRAME FULL [com/cedar/cglib/CglibTest$$EnhancerByCGLIB$$257d860e$$FastClassByCGLIB$$ef11584b java/lang/String [Ljava/lang/Class;] [[Ljava/lang/Class;]
    GOTO L24
   L11
   FRAME FULL [com/cedar/cglib/CglibTest$$EnhancerByCGLIB$$257d860e$$FastClassByCGLIB$$ef11584b java/lang/String [Ljava/lang/Class;] [[Ljava/lang/Class; java/lang/String]
    LDC "hashCode"
    INVOKEVIRTUAL java/lang/Object.equals (Ljava/lang/Object;)Z
    IFEQ L21
    DUP
    ARRAYLENGTH
    TABLESWITCH
      0: L45
      default: L46
   L45
   FRAME FULL [com/cedar/cglib/CglibTest$$EnhancerByCGLIB$$257d860e$$FastClassByCGLIB$$ef11584b java/lang/String [Ljava/lang/Class;] [[Ljava/lang/Class;]
    POP
    BIPUSH 16
    IRETURN
   L46
   FRAME FULL [com/cedar/cglib/CglibTest$$EnhancerByCGLIB$$257d860e$$FastClassByCGLIB$$ef11584b java/lang/String [Ljava/lang/Class;] [[Ljava/lang/Class;]
    GOTO L24
   L12
   FRAME FULL [com/cedar/cglib/CglibTest$$EnhancerByCGLIB$$257d860e$$FastClassByCGLIB$$ef11584b java/lang/String [Ljava/lang/Class;] [[Ljava/lang/Class; java/lang/String]
    LDC "CGLIB$STATICHOOK1"
    INVOKEVIRTUAL java/lang/Object.equals (Ljava/lang/Object;)Z
    IFEQ L21
    DUP
    ARRAYLENGTH
    TABLESWITCH
      0: L47
      default: L48
   L47
   FRAME FULL [com/cedar/cglib/CglibTest$$EnhancerByCGLIB$$257d860e$$FastClassByCGLIB$$ef11584b java/lang/String [Ljava/lang/Class;] [[Ljava/lang/Class;]
    POP
    BIPUSH 7
    IRETURN
   L48
   FRAME FULL [com/cedar/cglib/CglibTest$$EnhancerByCGLIB$$257d860e$$FastClassByCGLIB$$ef11584b java/lang/String [Ljava/lang/Class;] [[Ljava/lang/Class;]
    GOTO L24
   L13
   FRAME FULL [com/cedar/cglib/CglibTest$$EnhancerByCGLIB$$257d860e$$FastClassByCGLIB$$ef11584b java/lang/String [Ljava/lang/Class;] [[Ljava/lang/Class; java/lang/String]
    LDC "setCallbacks"
    INVOKEVIRTUAL java/lang/Object.equals (Ljava/lang/Object;)Z
    IFEQ L21
    DUP
    ARRAYLENGTH
    TABLESWITCH
      1: L49
      default: L50
   L49
   FRAME FULL [com/cedar/cglib/CglibTest$$EnhancerByCGLIB$$257d860e$$FastClassByCGLIB$$ef11584b java/lang/String [Ljava/lang/Class;] [[Ljava/lang/Class;]
    DUP
    ICONST_0
    AALOAD
    INVOKEVIRTUAL java/lang/Class.getName ()Ljava/lang/String;
    LDC "[Lnet.sf.cglib.proxy.Callback;"
    INVOKEVIRTUAL java/lang/Object.equals (Ljava/lang/Object;)Z
    IFEQ L24
    POP
    ICONST_2
    IRETURN
   L50
   FRAME FULL [com/cedar/cglib/CglibTest$$EnhancerByCGLIB$$257d860e$$FastClassByCGLIB$$ef11584b java/lang/String [Ljava/lang/Class;] [[Ljava/lang/Class;]
    GOTO L24
   L14
   FRAME FULL [com/cedar/cglib/CglibTest$$EnhancerByCGLIB$$257d860e$$FastClassByCGLIB$$ef11584b java/lang/String [Ljava/lang/Class;] [[Ljava/lang/Class; java/lang/String]
    LDC "CGLIB$findMethodProxy"
    INVOKEVIRTUAL java/lang/Object.equals (Ljava/lang/Object;)Z
    IFEQ L21
    DUP
    ARRAYLENGTH
    TABLESWITCH
      1: L51
      default: L52
   L51
   FRAME FULL [com/cedar/cglib/CglibTest$$EnhancerByCGLIB$$257d860e$$FastClassByCGLIB$$ef11584b java/lang/String [Ljava/lang/Class;] [[Ljava/lang/Class;]
    DUP
    ICONST_0
    AALOAD
    INVOKEVIRTUAL java/lang/Class.getName ()Ljava/lang/String;
    LDC "net.sf.cglib.core.Signature"
    INVOKEVIRTUAL java/lang/Object.equals (Ljava/lang/Object;)Z
    IFEQ L24
    POP
    BIPUSH 8
    IRETURN
   L52
   FRAME FULL [com/cedar/cglib/CglibTest$$EnhancerByCGLIB$$257d860e$$FastClassByCGLIB$$ef11584b java/lang/String [Ljava/lang/Class;] [[Ljava/lang/Class;]
    GOTO L24
   L15
   FRAME FULL [com/cedar/cglib/CglibTest$$EnhancerByCGLIB$$257d860e$$FastClassByCGLIB$$ef11584b java/lang/String [Ljava/lang/Class;] [[Ljava/lang/Class; java/lang/String]
    LDC "CGLIB$toString$2"
    INVOKEVIRTUAL java/lang/Object.equals (Ljava/lang/Object;)Z
    IFEQ L21
    DUP
    ARRAYLENGTH
    TABLESWITCH
      0: L53
      default: L54
   L53
   FRAME FULL [com/cedar/cglib/CglibTest$$EnhancerByCGLIB$$257d860e$$FastClassByCGLIB$$ef11584b java/lang/String [Ljava/lang/Class;] [[Ljava/lang/Class;]
    POP
    BIPUSH 13
    IRETURN
   L54
   FRAME FULL [com/cedar/cglib/CglibTest$$EnhancerByCGLIB$$257d860e$$FastClassByCGLIB$$ef11584b java/lang/String [Ljava/lang/Class;] [[Ljava/lang/Class;]
    GOTO L24
   L16
   FRAME FULL [com/cedar/cglib/CglibTest$$EnhancerByCGLIB$$257d860e$$FastClassByCGLIB$$ef11584b java/lang/String [Ljava/lang/Class;] [[Ljava/lang/Class; java/lang/String]
    LDC "newInstance"
    INVOKEVIRTUAL java/lang/Object.equals (Ljava/lang/Object;)Z
    IFEQ L21
    DUP
    ARRAYLENGTH
    TABLESWITCH
      1: L55
      2: L56
      3: L57
      default: L56
   L55
   FRAME FULL [com/cedar/cglib/CglibTest$$EnhancerByCGLIB$$257d860e$$FastClassByCGLIB$$ef11584b java/lang/String [Ljava/lang/Class;] [[Ljava/lang/Class;]
    DUP
    ICONST_0
    AALOAD
    INVOKEVIRTUAL java/lang/Class.getName ()Ljava/lang/String;
    DUP
    INVOKEVIRTUAL java/lang/Object.hashCode ()I
    LOOKUPSWITCH
      -845341380: L58
      1730110032: L59
      default: L60
   L58
   FRAME FULL [com/cedar/cglib/CglibTest$$EnhancerByCGLIB$$257d860e$$FastClassByCGLIB$$ef11584b java/lang/String [Ljava/lang/Class;] [[Ljava/lang/Class; java/lang/String]
    LDC "net.sf.cglib.proxy.Callback"
    INVOKEVIRTUAL java/lang/Object.equals (Ljava/lang/Object;)Z
    IFEQ L61
    POP
    BIPUSH 20
    IRETURN
   L59
   FRAME FULL [com/cedar/cglib/CglibTest$$EnhancerByCGLIB$$257d860e$$FastClassByCGLIB$$ef11584b java/lang/String [Ljava/lang/Class;] [[Ljava/lang/Class; java/lang/String]
    LDC "[Lnet.sf.cglib.proxy.Callback;"
    INVOKEVIRTUAL java/lang/Object.equals (Ljava/lang/Object;)Z
    IFEQ L61
    POP
    BIPUSH 18
    IRETURN
   L60
   FRAME FULL [com/cedar/cglib/CglibTest$$EnhancerByCGLIB$$257d860e$$FastClassByCGLIB$$ef11584b java/lang/String [Ljava/lang/Class;] [[Ljava/lang/Class; java/lang/String]
    POP
   L61
   FRAME FULL [com/cedar/cglib/CglibTest$$EnhancerByCGLIB$$257d860e$$FastClassByCGLIB$$ef11584b java/lang/String [Ljava/lang/Class;] [[Ljava/lang/Class;]
    GOTO L24
   L57
   FRAME FULL [com/cedar/cglib/CglibTest$$EnhancerByCGLIB$$257d860e$$FastClassByCGLIB$$ef11584b java/lang/String [Ljava/lang/Class;] [[Ljava/lang/Class;]
    DUP
    ICONST_0
    AALOAD
    INVOKEVIRTUAL java/lang/Class.getName ()Ljava/lang/String;
    LDC "[Ljava.lang.Class;"
    INVOKEVIRTUAL java/lang/Object.equals (Ljava/lang/Object;)Z
    IFEQ L24
    DUP
    ICONST_1
    AALOAD
    INVOKEVIRTUAL java/lang/Class.getName ()Ljava/lang/String;
    LDC "[Ljava.lang.Object;"
    INVOKEVIRTUAL java/lang/Object.equals (Ljava/lang/Object;)Z
    IFEQ L24
    DUP
    ICONST_2
    AALOAD
    INVOKEVIRTUAL java/lang/Class.getName ()Ljava/lang/String;
    LDC "[Lnet.sf.cglib.proxy.Callback;"
    INVOKEVIRTUAL java/lang/Object.equals (Ljava/lang/Object;)Z
    IFEQ L24
    POP
    BIPUSH 19
    IRETURN
   L56
   FRAME FULL [com/cedar/cglib/CglibTest$$EnhancerByCGLIB$$257d860e$$FastClassByCGLIB$$ef11584b java/lang/String [Ljava/lang/Class;] [[Ljava/lang/Class;]
    GOTO L24
   L17
   FRAME FULL [com/cedar/cglib/CglibTest$$EnhancerByCGLIB$$257d860e$$FastClassByCGLIB$$ef11584b java/lang/String [Ljava/lang/Class;] [[Ljava/lang/Class; java/lang/String]
    LDC "setCallback"
    INVOKEVIRTUAL java/lang/Object.equals (Ljava/lang/Object;)Z
    IFEQ L21
    DUP
    ARRAYLENGTH
    TABLESWITCH
      2: L62
      default: L63
   L62
   FRAME FULL [com/cedar/cglib/CglibTest$$EnhancerByCGLIB$$257d860e$$FastClassByCGLIB$$ef11584b java/lang/String [Ljava/lang/Class;] [[Ljava/lang/Class;]
    DUP
    ICONST_0
    AALOAD
    INVOKEVIRTUAL java/lang/Class.getName ()Ljava/lang/String;
    LDC "int"
    INVOKEVIRTUAL java/lang/Object.equals (Ljava/lang/Object;)Z
    IFEQ L24
    DUP
    ICONST_1
    AALOAD
    INVOKEVIRTUAL java/lang/Class.getName ()Ljava/lang/String;
    LDC "net.sf.cglib.proxy.Callback"
    INVOKEVIRTUAL java/lang/Object.equals (Ljava/lang/Object;)Z
    IFEQ L24
    POP
    ICONST_1
    IRETURN
   L63
   FRAME FULL [com/cedar/cglib/CglibTest$$EnhancerByCGLIB$$257d860e$$FastClassByCGLIB$$ef11584b java/lang/String [Ljava/lang/Class;] [[Ljava/lang/Class;]
    GOTO L24
   L18
   FRAME FULL [com/cedar/cglib/CglibTest$$EnhancerByCGLIB$$257d860e$$FastClassByCGLIB$$ef11584b java/lang/String [Ljava/lang/Class;] [[Ljava/lang/Class; java/lang/String]
    LDC "getCallback"
    INVOKEVIRTUAL java/lang/Object.equals (Ljava/lang/Object;)Z
    IFEQ L21
    DUP
    ARRAYLENGTH
    TABLESWITCH
      1: L64
      default: L65
   L64
   FRAME FULL [com/cedar/cglib/CglibTest$$EnhancerByCGLIB$$257d860e$$FastClassByCGLIB$$ef11584b java/lang/String [Ljava/lang/Class;] [[Ljava/lang/Class;]
    DUP
    ICONST_0
    AALOAD
    INVOKEVIRTUAL java/lang/Class.getName ()Ljava/lang/String;
    LDC "int"
    INVOKEVIRTUAL java/lang/Object.equals (Ljava/lang/Object;)Z
    IFEQ L24
    POP
    ICONST_5
    IRETURN
   L65
   FRAME FULL [com/cedar/cglib/CglibTest$$EnhancerByCGLIB$$257d860e$$FastClassByCGLIB$$ef11584b java/lang/String [Ljava/lang/Class;] [[Ljava/lang/Class;]
    GOTO L24
   L19
   FRAME FULL [com/cedar/cglib/CglibTest$$EnhancerByCGLIB$$257d860e$$FastClassByCGLIB$$ef11584b java/lang/String [Ljava/lang/Class;] [[Ljava/lang/Class; java/lang/String]
    LDC "CGLIB$clone$4"
    INVOKEVIRTUAL java/lang/Object.equals (Ljava/lang/Object;)Z
    IFEQ L21
    DUP
    ARRAYLENGTH
    TABLESWITCH
      0: L66
      default: L67
   L66
   FRAME FULL [com/cedar/cglib/CglibTest$$EnhancerByCGLIB$$257d860e$$FastClassByCGLIB$$ef11584b java/lang/String [Ljava/lang/Class;] [[Ljava/lang/Class;]
    POP
    BIPUSH 9
    IRETURN
   L67
   FRAME FULL [com/cedar/cglib/CglibTest$$EnhancerByCGLIB$$257d860e$$FastClassByCGLIB$$ef11584b java/lang/String [Ljava/lang/Class;] [[Ljava/lang/Class;]
    GOTO L24
   L20
   FRAME FULL [com/cedar/cglib/CglibTest$$EnhancerByCGLIB$$257d860e$$FastClassByCGLIB$$ef11584b java/lang/String [Ljava/lang/Class;] [[Ljava/lang/Class; java/lang/String]
    POP
   L21
   FRAME FULL [com/cedar/cglib/CglibTest$$EnhancerByCGLIB$$257d860e$$FastClassByCGLIB$$ef11584b java/lang/String [Ljava/lang/Class;] [[Ljava/lang/Class;]
    GOTO L24
   L24
   FRAME FULL [com/cedar/cglib/CglibTest$$EnhancerByCGLIB$$257d860e$$FastClassByCGLIB$$ef11584b java/lang/String [Ljava/lang/Class;] [[Ljava/lang/Class;]
    POP
    ICONST_M1
    IRETURN
    MAXSTACK = 3
    MAXLOCALS = 3

  // access flags 0x1
  public getIndex([Ljava/lang/Class;)I
    ALOAD 1
    DUP
    ARRAYLENGTH
    TABLESWITCH
      0: L0
      default: L1
   L0
   FRAME FULL [com/cedar/cglib/CglibTest$$EnhancerByCGLIB$$257d860e$$FastClassByCGLIB$$ef11584b [Ljava/lang/Class;] [[Ljava/lang/Class;]
    POP
    ICONST_0
    IRETURN
   L1
   FRAME FULL [com/cedar/cglib/CglibTest$$EnhancerByCGLIB$$257d860e$$FastClassByCGLIB$$ef11584b [Ljava/lang/Class;] [[Ljava/lang/Class;]
    GOTO L2
   L2
   FRAME FULL [com/cedar/cglib/CglibTest$$EnhancerByCGLIB$$257d860e$$FastClassByCGLIB$$ef11584b [Ljava/lang/Class;] [[Ljava/lang/Class;]
    POP
    ICONST_M1
    IRETURN
    MAXSTACK = 2
    MAXLOCALS = 2

  // access flags 0x1
  public invoke(ILjava/lang/Object;[Ljava/lang/Object;)Ljava/lang/Object; throws java/lang/reflect/InvocationTargetException 
    TRYCATCHBLOCK L0 L1 L1 java/lang/Throwable
    ALOAD 2
    CHECKCAST com/cedar/cglib/CglibTest$$EnhancerByCGLIB$$257d860e
    ILOAD 1
   L0
    TABLESWITCH
      0: L2
      1: L3
      2: L4
      3: L5
      4: L6
      5: L7
      6: L8
      7: L9
      8: L10
      9: L11
      10: L12
      11: L13
      12: L14
      13: L15
      14: L16
      15: L17
      16: L18
      17: L19
      18: L20
      19: L21
      20: L22
      21: L23
      default: L24
   L2
   FRAME FULL [com/cedar/cglib/CglibTest$$EnhancerByCGLIB$$257d860e$$FastClassByCGLIB$$ef11584b I java/lang/Object [Ljava/lang/Object;] [com/cedar/cglib/CglibTest$$EnhancerByCGLIB$$257d860e]
    ALOAD 3
    ICONST_0
    AALOAD
    CHECKCAST java/lang/String
    INVOKEVIRTUAL com/cedar/cglib/CglibTest$$EnhancerByCGLIB$$257d860e.operate1 (Ljava/lang/String;)Ljava/lang/String;
    ARETURN
   L3
   FRAME FULL [com/cedar/cglib/CglibTest$$EnhancerByCGLIB$$257d860e$$FastClassByCGLIB$$ef11584b I java/lang/Object [Ljava/lang/Object;] [com/cedar/cglib/CglibTest$$EnhancerByCGLIB$$257d860e]
    ALOAD 3
    ICONST_0
    AALOAD
    CHECKCAST java/lang/Number
    INVOKEVIRTUAL java/lang/Number.intValue ()I
    ALOAD 3
    ICONST_1
    AALOAD
    CHECKCAST net/sf/cglib/proxy/Callback
    INVOKEVIRTUAL com/cedar/cglib/CglibTest$$EnhancerByCGLIB$$257d860e.setCallback (ILnet/sf/cglib/proxy/Callback;)V
    ACONST_NULL
    ARETURN
   L4
   FRAME FULL [com/cedar/cglib/CglibTest$$EnhancerByCGLIB$$257d860e$$FastClassByCGLIB$$ef11584b I java/lang/Object [Ljava/lang/Object;] [com/cedar/cglib/CglibTest$$EnhancerByCGLIB$$257d860e]
    ALOAD 3
    ICONST_0
    AALOAD
    CHECKCAST [Lnet/sf/cglib/proxy/Callback;
    INVOKEVIRTUAL com/cedar/cglib/CglibTest$$EnhancerByCGLIB$$257d860e.setCallbacks ([Lnet/sf/cglib/proxy/Callback;)V
    ACONST_NULL
    ARETURN
   L5
   FRAME FULL [com/cedar/cglib/CglibTest$$EnhancerByCGLIB$$257d860e$$FastClassByCGLIB$$ef11584b I java/lang/Object [Ljava/lang/Object;] [com/cedar/cglib/CglibTest$$EnhancerByCGLIB$$257d860e]
    ALOAD 3
    ICONST_0
    AALOAD
    CHECKCAST [Lnet/sf/cglib/proxy/Callback;
    INVOKESTATIC com/cedar/cglib/CglibTest$$EnhancerByCGLIB$$257d860e.CGLIB$SET_STATIC_CALLBACKS ([Lnet/sf/cglib/proxy/Callback;)V
    ACONST_NULL
    ARETURN
   L6
   FRAME FULL [com/cedar/cglib/CglibTest$$EnhancerByCGLIB$$257d860e$$FastClassByCGLIB$$ef11584b I java/lang/Object [Ljava/lang/Object;] [com/cedar/cglib/CglibTest$$EnhancerByCGLIB$$257d860e]
    ALOAD 3
    ICONST_0
    AALOAD
    CHECKCAST [Lnet/sf/cglib/proxy/Callback;
    INVOKESTATIC com/cedar/cglib/CglibTest$$EnhancerByCGLIB$$257d860e.CGLIB$SET_THREAD_CALLBACKS ([Lnet/sf/cglib/proxy/Callback;)V
    ACONST_NULL
    ARETURN
   L7
   FRAME FULL [com/cedar/cglib/CglibTest$$EnhancerByCGLIB$$257d860e$$FastClassByCGLIB$$ef11584b I java/lang/Object [Ljava/lang/Object;] [com/cedar/cglib/CglibTest$$EnhancerByCGLIB$$257d860e]
    ALOAD 3
    ICONST_0
    AALOAD
    CHECKCAST java/lang/Number
    INVOKEVIRTUAL java/lang/Number.intValue ()I
    INVOKEVIRTUAL com/cedar/cglib/CglibTest$$EnhancerByCGLIB$$257d860e.getCallback (I)Lnet/sf/cglib/proxy/Callback;
    ARETURN
   L8
   FRAME FULL [com/cedar/cglib/CglibTest$$EnhancerByCGLIB$$257d860e$$FastClassByCGLIB$$ef11584b I java/lang/Object [Ljava/lang/Object;] [com/cedar/cglib/CglibTest$$EnhancerByCGLIB$$257d860e]
    INVOKEVIRTUAL com/cedar/cglib/CglibTest$$EnhancerByCGLIB$$257d860e.getCallbacks ()[Lnet/sf/cglib/proxy/Callback;
    ARETURN
   L9
   FRAME FULL [com/cedar/cglib/CglibTest$$EnhancerByCGLIB$$257d860e$$FastClassByCGLIB$$ef11584b I java/lang/Object [Ljava/lang/Object;] [com/cedar/cglib/CglibTest$$EnhancerByCGLIB$$257d860e]
    INVOKESTATIC com/cedar/cglib/CglibTest$$EnhancerByCGLIB$$257d860e.CGLIB$STATICHOOK1 ()V
    ACONST_NULL
    ARETURN
   L10
   FRAME FULL [com/cedar/cglib/CglibTest$$EnhancerByCGLIB$$257d860e$$FastClassByCGLIB$$ef11584b I java/lang/Object [Ljava/lang/Object;] [com/cedar/cglib/CglibTest$$EnhancerByCGLIB$$257d860e]
    ALOAD 3
    ICONST_0
    AALOAD
    CHECKCAST net/sf/cglib/core/Signature
    INVOKESTATIC com/cedar/cglib/CglibTest$$EnhancerByCGLIB$$257d860e.CGLIB$findMethodProxy (Lnet/sf/cglib/core/Signature;)Lnet/sf/cglib/proxy/MethodProxy;
    ARETURN
   L11
   FRAME FULL [com/cedar/cglib/CglibTest$$EnhancerByCGLIB$$257d860e$$FastClassByCGLIB$$ef11584b I java/lang/Object [Ljava/lang/Object;] [com/cedar/cglib/CglibTest$$EnhancerByCGLIB$$257d860e]
    INVOKEVIRTUAL com/cedar/cglib/CglibTest$$EnhancerByCGLIB$$257d860e.CGLIB$clone$4 ()Ljava/lang/Object;
    ARETURN
   L12
   FRAME FULL [com/cedar/cglib/CglibTest$$EnhancerByCGLIB$$257d860e$$FastClassByCGLIB$$ef11584b I java/lang/Object [Ljava/lang/Object;] [com/cedar/cglib/CglibTest$$EnhancerByCGLIB$$257d860e]
    ALOAD 3
    ICONST_0
    AALOAD
    CHECKCAST java/lang/String
    INVOKEVIRTUAL com/cedar/cglib/CglibTest$$EnhancerByCGLIB$$257d860e.CGLIB$operate1$0 (Ljava/lang/String;)Ljava/lang/String;
    ARETURN
   L13
   FRAME FULL [com/cedar/cglib/CglibTest$$EnhancerByCGLIB$$257d860e$$FastClassByCGLIB$$ef11584b I java/lang/Object [Ljava/lang/Object;] [com/cedar/cglib/CglibTest$$EnhancerByCGLIB$$257d860e]
    INVOKEVIRTUAL com/cedar/cglib/CglibTest$$EnhancerByCGLIB$$257d860e.CGLIB$hashCode$3 ()I
    NEW java/lang/Integer
    DUP_X1
    SWAP
    INVOKESPECIAL java/lang/Integer.<init> (I)V
    ARETURN
   L14
   FRAME FULL [com/cedar/cglib/CglibTest$$EnhancerByCGLIB$$257d860e$$FastClassByCGLIB$$ef11584b I java/lang/Object [Ljava/lang/Object;] [com/cedar/cglib/CglibTest$$EnhancerByCGLIB$$257d860e]
    ALOAD 3
    ICONST_0
    AALOAD
    INVOKEVIRTUAL com/cedar/cglib/CglibTest$$EnhancerByCGLIB$$257d860e.CGLIB$equals$1 (Ljava/lang/Object;)Z
    NEW java/lang/Boolean
    DUP_X1
    SWAP
    INVOKESPECIAL java/lang/Boolean.<init> (Z)V
    ARETURN
   L15
   FRAME FULL [com/cedar/cglib/CglibTest$$EnhancerByCGLIB$$257d860e$$FastClassByCGLIB$$ef11584b I java/lang/Object [Ljava/lang/Object;] [com/cedar/cglib/CglibTest$$EnhancerByCGLIB$$257d860e]
    INVOKEVIRTUAL com/cedar/cglib/CglibTest$$EnhancerByCGLIB$$257d860e.CGLIB$toString$2 ()Ljava/lang/String;
    ARETURN
   L16
   FRAME FULL [com/cedar/cglib/CglibTest$$EnhancerByCGLIB$$257d860e$$FastClassByCGLIB$$ef11584b I java/lang/Object [Ljava/lang/Object;] [com/cedar/cglib/CglibTest$$EnhancerByCGLIB$$257d860e]
    ALOAD 3
    ICONST_0
    AALOAD
    INVOKEVIRTUAL com/cedar/cglib/CglibTest$$EnhancerByCGLIB$$257d860e.equals (Ljava/lang/Object;)Z
    NEW java/lang/Boolean
    DUP_X1
    SWAP
    INVOKESPECIAL java/lang/Boolean.<init> (Z)V
    ARETURN
   L17
   FRAME FULL [com/cedar/cglib/CglibTest$$EnhancerByCGLIB$$257d860e$$FastClassByCGLIB$$ef11584b I java/lang/Object [Ljava/lang/Object;] [com/cedar/cglib/CglibTest$$EnhancerByCGLIB$$257d860e]
    INVOKEVIRTUAL com/cedar/cglib/CglibTest$$EnhancerByCGLIB$$257d860e.toString ()Ljava/lang/String;
    ARETURN
   L18
   FRAME FULL [com/cedar/cglib/CglibTest$$EnhancerByCGLIB$$257d860e$$FastClassByCGLIB$$ef11584b I java/lang/Object [Ljava/lang/Object;] [com/cedar/cglib/CglibTest$$EnhancerByCGLIB$$257d860e]
    INVOKEVIRTUAL com/cedar/cglib/CglibTest$$EnhancerByCGLIB$$257d860e.hashCode ()I
    NEW java/lang/Integer
    DUP_X1
    SWAP
    INVOKESPECIAL java/lang/Integer.<init> (I)V
    ARETURN
   L19
   FRAME FULL [com/cedar/cglib/CglibTest$$EnhancerByCGLIB$$257d860e$$FastClassByCGLIB$$ef11584b I java/lang/Object [Ljava/lang/Object;] [com/cedar/cglib/CglibTest$$EnhancerByCGLIB$$257d860e]
    INVOKEVIRTUAL com/cedar/cglib/CglibTest$$EnhancerByCGLIB$$257d860e.clone ()Ljava/lang/Object;
    ARETURN
   L20
   FRAME FULL [com/cedar/cglib/CglibTest$$EnhancerByCGLIB$$257d860e$$FastClassByCGLIB$$ef11584b I java/lang/Object [Ljava/lang/Object;] [com/cedar/cglib/CglibTest$$EnhancerByCGLIB$$257d860e]
    ALOAD 3
    ICONST_0
    AALOAD
    CHECKCAST [Lnet/sf/cglib/proxy/Callback;
    INVOKEVIRTUAL com/cedar/cglib/CglibTest$$EnhancerByCGLIB$$257d860e.newInstance ([Lnet/sf/cglib/proxy/Callback;)Ljava/lang/Object;
    ARETURN
   L21
   FRAME FULL [com/cedar/cglib/CglibTest$$EnhancerByCGLIB$$257d860e$$FastClassByCGLIB$$ef11584b I java/lang/Object [Ljava/lang/Object;] [com/cedar/cglib/CglibTest$$EnhancerByCGLIB$$257d860e]
    ALOAD 3
    ICONST_0
    AALOAD
    CHECKCAST [Ljava/lang/Class;
    ALOAD 3
    ICONST_1
    AALOAD
    CHECKCAST [Ljava/lang/Object;
    ALOAD 3
    ICONST_2
    AALOAD
    CHECKCAST [Lnet/sf/cglib/proxy/Callback;
    INVOKEVIRTUAL com/cedar/cglib/CglibTest$$EnhancerByCGLIB$$257d860e.newInstance ([Ljava/lang/Class;[Ljava/lang/Object;[Lnet/sf/cglib/proxy/Callback;)Ljava/lang/Object;
    ARETURN
   L22
   FRAME FULL [com/cedar/cglib/CglibTest$$EnhancerByCGLIB$$257d860e$$FastClassByCGLIB$$ef11584b I java/lang/Object [Ljava/lang/Object;] [com/cedar/cglib/CglibTest$$EnhancerByCGLIB$$257d860e]
    ALOAD 3
    ICONST_0
    AALOAD
    CHECKCAST net/sf/cglib/proxy/Callback
    INVOKEVIRTUAL com/cedar/cglib/CglibTest$$EnhancerByCGLIB$$257d860e.newInstance (Lnet/sf/cglib/proxy/Callback;)Ljava/lang/Object;
    ARETURN
   L23
   FRAME FULL [com/cedar/cglib/CglibTest$$EnhancerByCGLIB$$257d860e$$FastClassByCGLIB$$ef11584b I java/lang/Object [Ljava/lang/Object;] [com/cedar/cglib/CglibTest$$EnhancerByCGLIB$$257d860e]
    ALOAD 3
    ICONST_0
    AALOAD
    CHECKCAST [Ljava/lang/String;
    INVOKESTATIC com/cedar/cglib/CglibTest.main ([Ljava/lang/String;)V
    ACONST_NULL
    ARETURN
   L24
   FRAME FULL [com/cedar/cglib/CglibTest$$EnhancerByCGLIB$$257d860e$$FastClassByCGLIB$$ef11584b I java/lang/Object [Ljava/lang/Object;] [com/cedar/cglib/CglibTest$$EnhancerByCGLIB$$257d860e]
    GOTO L25
   L1
   FRAME FULL [com/cedar/cglib/CglibTest$$EnhancerByCGLIB$$257d860e$$FastClassByCGLIB$$ef11584b I java/lang/Object [Ljava/lang/Object;] [java/lang/Throwable]
    NEW java/lang/reflect/InvocationTargetException
    DUP_X1
    SWAP
    INVOKESPECIAL java/lang/reflect/InvocationTargetException.<init> (Ljava/lang/Throwable;)V
    ATHROW
   L25
   FRAME FULL [com/cedar/cglib/CglibTest$$EnhancerByCGLIB$$257d860e$$FastClassByCGLIB$$ef11584b I java/lang/Object [Ljava/lang/Object;] [com/cedar/cglib/CglibTest$$EnhancerByCGLIB$$257d860e]
    NEW java/lang/IllegalArgumentException
    DUP
    LDC "Cannot find matching method/constructor"
    INVOKESPECIAL java/lang/IllegalArgumentException.<init> (Ljava/lang/String;)V
    ATHROW
    MAXSTACK = 5
    MAXLOCALS = 4

  // access flags 0x1
  public newInstance(I[Ljava/lang/Object;)Ljava/lang/Object; throws java/lang/reflect/InvocationTargetException 
    TRYCATCHBLOCK L0 L1 L1 java/lang/Throwable
   L2
    NEW com/cedar/cglib/CglibTest$$EnhancerByCGLIB$$257d860e
    DUP
    ILOAD 1
   L0
    TABLESWITCH
      0: L3
      default: L4
   L3
   FRAME FULL [com/cedar/cglib/CglibTest$$EnhancerByCGLIB$$257d860e$$FastClassByCGLIB$$ef11584b I [Ljava/lang/Object;] [L2 L2]
    INVOKESPECIAL com/cedar/cglib/CglibTest$$EnhancerByCGLIB$$257d860e.<init> ()V
    ARETURN
   L4
   FRAME FULL [com/cedar/cglib/CglibTest$$EnhancerByCGLIB$$257d860e$$FastClassByCGLIB$$ef11584b I [Ljava/lang/Object;] [L2 L2]
    GOTO L5
   L1
   FRAME FULL [com/cedar/cglib/CglibTest$$EnhancerByCGLIB$$257d860e$$FastClassByCGLIB$$ef11584b I [Ljava/lang/Object;] [java/lang/Throwable]
    NEW java/lang/reflect/InvocationTargetException
    DUP_X1
    SWAP
    INVOKESPECIAL java/lang/reflect/InvocationTargetException.<init> (Ljava/lang/Throwable;)V
    ATHROW
   L5
   FRAME FULL [com/cedar/cglib/CglibTest$$EnhancerByCGLIB$$257d860e$$FastClassByCGLIB$$ef11584b I [Ljava/lang/Object;] [L2 L2]
    NEW java/lang/IllegalArgumentException
    DUP
    LDC "Cannot find matching method/constructor"
    INVOKESPECIAL java/lang/IllegalArgumentException.<init> (Ljava/lang/String;)V
    ATHROW
    MAXSTACK = 5
    MAXLOCALS = 3

  // access flags 0x1
  public getMaxIndex()I
    BIPUSH 21
    IRETURN
    MAXSTACK = 1
    MAXLOCALS = 1
}
